{
    "/js/app.js": "/js/app.js",
    "/js/app.3b3c098a4e8d28bb13db.hot-update.js": "/js/app.3b3c098a4e8d28bb13db.hot-update.js",
    "/js/app.c0bba49f6761bf4d96e7.hot-update.js": "/js/app.c0bba49f6761bf4d96e7.hot-update.js",
    "/js/app.a6fdec700615767dc400.hot-update.js": "/js/app.a6fdec700615767dc400.hot-update.js",
    "/js/app.36df38c60213d4f4d1a5.hot-update.js": "/js/app.36df38c60213d4f4d1a5.hot-update.js",
    "/js/app.64684cfb34d1b3120926.hot-update.js": "/js/app.64684cfb34d1b3120926.hot-update.js",
    "/js/app.f8b8ae1a998329693a22.hot-update.js": "/js/app.f8b8ae1a998329693a22.hot-update.js",
    "/js/app.3b23d5ae16236dc4178e.hot-update.js": "/js/app.3b23d5ae16236dc4178e.hot-update.js",
    "/js/app.7615b89d4198cdb9b314.hot-update.js": "/js/app.7615b89d4198cdb9b314.hot-update.js",
    "/js/app.66349eeeddceaea2f16f.hot-update.js": "/js/app.66349eeeddceaea2f16f.hot-update.js",
    "/js/app.e1914353f04af789cb28.hot-update.js": "/js/app.e1914353f04af789cb28.hot-update.js",
    "/js/app.6a4aea254a49359515a9.hot-update.js": "/js/app.6a4aea254a49359515a9.hot-update.js",
    "/js/app.c66f100351b5e11f69f1.hot-update.js": "/js/app.c66f100351b5e11f69f1.hot-update.js",
    "/js/app.c21d6586a0b3ffa93c55.hot-update.js": "/js/app.c21d6586a0b3ffa93c55.hot-update.js",
    "/js/app.77e101621b13505494cf.hot-update.js": "/js/app.77e101621b13505494cf.hot-update.js",
    "/js/app.fe40443a0d219fe08eb8.hot-update.js": "/js/app.fe40443a0d219fe08eb8.hot-update.js",
    "/js/app.9f5f572e97399c75bd72.hot-update.js": "/js/app.9f5f572e97399c75bd72.hot-update.js",
    "/js/app.2e4ff9de1bacb7667bef.hot-update.js": "/js/app.2e4ff9de1bacb7667bef.hot-update.js",
    "/js/app.6640c6947f90b8d95c2e.hot-update.js": "/js/app.6640c6947f90b8d95c2e.hot-update.js",
    "/js/app.c0ed0f42aa174c89ba97.hot-update.js": "/js/app.c0ed0f42aa174c89ba97.hot-update.js",
    "/js/app.8b26d43391afc88c9477.hot-update.js": "/js/app.8b26d43391afc88c9477.hot-update.js",
    "/js/app.b62066c9230e855961b4.hot-update.js": "/js/app.b62066c9230e855961b4.hot-update.js",
    "/js/app.ec6e01a71dc2133e4780.hot-update.js": "/js/app.ec6e01a71dc2133e4780.hot-update.js",
    "/js/app.aff5ceda9291e13f2d50.hot-update.js": "/js/app.aff5ceda9291e13f2d50.hot-update.js",
    "/js/app.07216e701475fce34939.hot-update.js": "/js/app.07216e701475fce34939.hot-update.js",
    "/js/app.5c22fe7f14b8ec5636e8.hot-update.js": "/js/app.5c22fe7f14b8ec5636e8.hot-update.js",
    "/js/app.b04ca48f3c9f15955440.hot-update.js": "/js/app.b04ca48f3c9f15955440.hot-update.js",
    "/js/app.4f4ad982be9c13c256c2.hot-update.js": "/js/app.4f4ad982be9c13c256c2.hot-update.js",
    "/js/app.e38e11d4a788d3282370.hot-update.js": "/js/app.e38e11d4a788d3282370.hot-update.js",
    "/js/app.f526f4889a1187e1a999.hot-update.js": "/js/app.f526f4889a1187e1a999.hot-update.js",
    "/js/app.c427d4ebc882e96038c0.hot-update.js": "/js/app.c427d4ebc882e96038c0.hot-update.js",
    "/js/app.d7c6ce74b88a1e2dc3b0.hot-update.js": "/js/app.d7c6ce74b88a1e2dc3b0.hot-update.js",
    "/js/app.74ec7e06dadc4c5dbe16.hot-update.js": "/js/app.74ec7e06dadc4c5dbe16.hot-update.js",
    "/js/app.736a77e6c10d6610507c.hot-update.js": "/js/app.736a77e6c10d6610507c.hot-update.js",
    "/js/app.c6832c9df816af6f2959.hot-update.js": "/js/app.c6832c9df816af6f2959.hot-update.js",
    "/js/app.d34ea535c5ac7e384173.hot-update.js": "/js/app.d34ea535c5ac7e384173.hot-update.js",
    "/js/app.5d571597b0454064ea49.hot-update.js": "/js/app.5d571597b0454064ea49.hot-update.js",
    "/js/app.73408db233fff7ec4503.hot-update.js": "/js/app.73408db233fff7ec4503.hot-update.js",
    "/js/app.9ffbbeae09329b8c9737.hot-update.js": "/js/app.9ffbbeae09329b8c9737.hot-update.js",
    "/js/app.59755ea0516284d4dd0f.hot-update.js": "/js/app.59755ea0516284d4dd0f.hot-update.js",
    "/js/app.81546d0ddd417dd6d8ea.hot-update.js": "/js/app.81546d0ddd417dd6d8ea.hot-update.js",
    "/js/app.d98aa20a22947434e0b9.hot-update.js": "/js/app.d98aa20a22947434e0b9.hot-update.js",
    "/js/app.bf7be59d8490b095f286.hot-update.js": "/js/app.bf7be59d8490b095f286.hot-update.js",
    "/js/app.7d8d54305462b5a1e197.hot-update.js": "/js/app.7d8d54305462b5a1e197.hot-update.js",
    "/js/app.f68b9f787f7cd0d28393.hot-update.js": "/js/app.f68b9f787f7cd0d28393.hot-update.js",
    "/js/app.629273f786db23fa1a93.hot-update.js": "/js/app.629273f786db23fa1a93.hot-update.js",
    "/js/app.7114fff33f721040f92c.hot-update.js": "/js/app.7114fff33f721040f92c.hot-update.js",
    "/js/app.982e5fdba195ca5611b0.hot-update.js": "/js/app.982e5fdba195ca5611b0.hot-update.js",
    "/js/app.2264abb3fbdb1f8fe1b6.hot-update.js": "/js/app.2264abb3fbdb1f8fe1b6.hot-update.js",
    "/js/app.b5cf440b975c45cacea6.hot-update.js": "/js/app.b5cf440b975c45cacea6.hot-update.js",
    "/js/app.11f6874e85d664f93eef.hot-update.js": "/js/app.11f6874e85d664f93eef.hot-update.js",
    "/js/app.558ef6bae1f3f928bd73.hot-update.js": "/js/app.558ef6bae1f3f928bd73.hot-update.js",
    "/js/app.e788b417c8fa5dfb34eb.hot-update.js": "/js/app.e788b417c8fa5dfb34eb.hot-update.js",
    "/js/app.355fe7114722701f75fe.hot-update.js": "/js/app.355fe7114722701f75fe.hot-update.js",
    "/js/app.5653bc95157571f25d90.hot-update.js": "/js/app.5653bc95157571f25d90.hot-update.js",
    "/js/app.22874abec57ffe081940.hot-update.js": "/js/app.22874abec57ffe081940.hot-update.js",
    "/js/app.a36bd3f53df8a5940b76.hot-update.js": "/js/app.a36bd3f53df8a5940b76.hot-update.js",
    "/js/app.affc95c401ba1919f41c.hot-update.js": "/js/app.affc95c401ba1919f41c.hot-update.js",
    "/js/app.85ff474151f64a99463a.hot-update.js": "/js/app.85ff474151f64a99463a.hot-update.js",
    "/js/app.4d5b1d11e54db3e2e61b.hot-update.js": "/js/app.4d5b1d11e54db3e2e61b.hot-update.js",
    "/js/app.7150156e2ab7f460ae81.hot-update.js": "/js/app.7150156e2ab7f460ae81.hot-update.js",
    "/js/app.f87786b757e35a1700e9.hot-update.js": "/js/app.f87786b757e35a1700e9.hot-update.js",
    "/js/app.5f5d5a218b5e4299c279.hot-update.js": "/js/app.5f5d5a218b5e4299c279.hot-update.js",
    "/js/app.fe562a427d3dfcf25fbb.hot-update.js": "/js/app.fe562a427d3dfcf25fbb.hot-update.js",
    "/js/app.b01832e7478c6287e6e4.hot-update.js": "/js/app.b01832e7478c6287e6e4.hot-update.js",
    "/js/app.ad1f6bfa3c71dfb824dd.hot-update.js": "/js/app.ad1f6bfa3c71dfb824dd.hot-update.js",
    "/js/app.38933d9cdc7c0a5c4b6e.hot-update.js": "/js/app.38933d9cdc7c0a5c4b6e.hot-update.js",
    "/js/app.97366c635afeb1e04819.hot-update.js": "/js/app.97366c635afeb1e04819.hot-update.js",
    "/js/app.3b17549a583908b076d1.hot-update.js": "/js/app.3b17549a583908b076d1.hot-update.js",
    "/js/app.582a3167ceeae05be929.hot-update.js": "/js/app.582a3167ceeae05be929.hot-update.js",
    "/js/app.eea6297fc4c2e7a5207d.hot-update.js": "/js/app.eea6297fc4c2e7a5207d.hot-update.js",
    "/js/app.ee88022b30bd59c21292.hot-update.js": "/js/app.ee88022b30bd59c21292.hot-update.js",
    "/js/app.d3364981379bfd767140.hot-update.js": "/js/app.d3364981379bfd767140.hot-update.js",
    "/js/app.77698507efa416b1fc74.hot-update.js": "/js/app.77698507efa416b1fc74.hot-update.js",
    "/js/app.72ed6b37aa4a9d38bfcf.hot-update.js": "/js/app.72ed6b37aa4a9d38bfcf.hot-update.js",
    "/js/app.fdd60cebb472a0c876d7.hot-update.js": "/js/app.fdd60cebb472a0c876d7.hot-update.js",
    "/js/app.066d7f58a93f606a9ffc.hot-update.js": "/js/app.066d7f58a93f606a9ffc.hot-update.js",
    "/js/app.badd8e4978fcf53bc921.hot-update.js": "/js/app.badd8e4978fcf53bc921.hot-update.js",
    "/js/app.ff7ae6758aca18a93570.hot-update.js": "/js/app.ff7ae6758aca18a93570.hot-update.js",
    "/js/app.80682757dcca1e37cdf8.hot-update.js": "/js/app.80682757dcca1e37cdf8.hot-update.js",
    "/js/app.6798682454463c01aafc.hot-update.js": "/js/app.6798682454463c01aafc.hot-update.js",
    "/js/app.34e800e943c32a6a7ebb.hot-update.js": "/js/app.34e800e943c32a6a7ebb.hot-update.js",
    "/js/app.3c5a3ea58593f46ac43b.hot-update.js": "/js/app.3c5a3ea58593f46ac43b.hot-update.js",
    "/js/app.ffabdd97d45d68d212a3.hot-update.js": "/js/app.ffabdd97d45d68d212a3.hot-update.js",
    "/js/app.7eb1e618a7ff418f99f5.hot-update.js": "/js/app.7eb1e618a7ff418f99f5.hot-update.js",
    "/js/app.20d5e388466d180b21ec.hot-update.js": "/js/app.20d5e388466d180b21ec.hot-update.js",
    "/js/app.59b0bf473cb6ae7ab1e1.hot-update.js": "/js/app.59b0bf473cb6ae7ab1e1.hot-update.js",
    "/js/app.499aed2e5062897f5f45.hot-update.js": "/js/app.499aed2e5062897f5f45.hot-update.js"
}
