{
    "/js/app.js": "/js/app.js",
    "/js/app.b826ebaedda4b7317ee5.hot-update.js": "/js/app.b826ebaedda4b7317ee5.hot-update.js",
    "/js/app.a9c5dcfaf6d019dd6cb6.hot-update.js": "/js/app.a9c5dcfaf6d019dd6cb6.hot-update.js",
    "/js/app.1b4ebab47e67fb099116.hot-update.js": "/js/app.1b4ebab47e67fb099116.hot-update.js",
    "/js/app.56f2078eb35bd1072635.hot-update.js": "/js/app.56f2078eb35bd1072635.hot-update.js",
    "/js/app.bc99d17ea1248ce23157.hot-update.js": "/js/app.bc99d17ea1248ce23157.hot-update.js",
    "/js/app.75e34fb41fdcca78d6cc.hot-update.js": "/js/app.75e34fb41fdcca78d6cc.hot-update.js",
    "/js/app.4a18362ecdcbf5c2129c.hot-update.js": "/js/app.4a18362ecdcbf5c2129c.hot-update.js",
    "/js/app.3c6d5da16287218a4be2.hot-update.js": "/js/app.3c6d5da16287218a4be2.hot-update.js",
    "/js/app.6966091d8dfc09fc927c.hot-update.js": "/js/app.6966091d8dfc09fc927c.hot-update.js",
    "/js/app.afe7c6ee91497ac77cb7.hot-update.js": "/js/app.afe7c6ee91497ac77cb7.hot-update.js",
    "/js/app.1f57b897ee58e76bfcca.hot-update.js": "/js/app.1f57b897ee58e76bfcca.hot-update.js",
    "/js/app.8d128626bee443a72c12.hot-update.js": "/js/app.8d128626bee443a72c12.hot-update.js",
    "/js/app.b58979400c52f1c7d448.hot-update.js": "/js/app.b58979400c52f1c7d448.hot-update.js",
    "/js/app.4a5be0be37d15b82b45a.hot-update.js": "/js/app.4a5be0be37d15b82b45a.hot-update.js",
    "/js/app.529ff26b5871680f7288.hot-update.js": "/js/app.529ff26b5871680f7288.hot-update.js",
    "/js/app.5a14b453e27a0b07a075.hot-update.js": "/js/app.5a14b453e27a0b07a075.hot-update.js",
    "/js/app.0daf180fb6b9b3cd94ae.hot-update.js": "/js/app.0daf180fb6b9b3cd94ae.hot-update.js",
    "/js/app.905b00d9e44ab342c150.hot-update.js": "/js/app.905b00d9e44ab342c150.hot-update.js",
    "/js/app.14f330dc87e40e2352e4.hot-update.js": "/js/app.14f330dc87e40e2352e4.hot-update.js",
    "/js/app.d3a7a48eb2df89de6f5c.hot-update.js": "/js/app.d3a7a48eb2df89de6f5c.hot-update.js",
    "/js/app.a9cf43c669a699782e40.hot-update.js": "/js/app.a9cf43c669a699782e40.hot-update.js",
    "/js/app.66268cd10e675ef3c6f0.hot-update.js": "/js/app.66268cd10e675ef3c6f0.hot-update.js",
    "/js/app.e7f31a05a9bfd2612b51.hot-update.js": "/js/app.e7f31a05a9bfd2612b51.hot-update.js",
    "/js/app.0c2b38a82954e1f418a5.hot-update.js": "/js/app.0c2b38a82954e1f418a5.hot-update.js",
    "/js/app.f6fa7a7d16a45e1b8790.hot-update.js": "/js/app.f6fa7a7d16a45e1b8790.hot-update.js",
    "/js/app.5b45a9cac86c6c9bfaa8.hot-update.js": "/js/app.5b45a9cac86c6c9bfaa8.hot-update.js",
    "/js/app.d95feec9900558c5b3e9.hot-update.js": "/js/app.d95feec9900558c5b3e9.hot-update.js",
    "/js/app.de121a7b43f75cf4e268.hot-update.js": "/js/app.de121a7b43f75cf4e268.hot-update.js",
    "/js/app.af4dac3992f1a7ab7b02.hot-update.js": "/js/app.af4dac3992f1a7ab7b02.hot-update.js",
    "/js/app.8ea8d9ff06fe74a4e312.hot-update.js": "/js/app.8ea8d9ff06fe74a4e312.hot-update.js",
    "/js/app.b2971c25f2dde438c03d.hot-update.js": "/js/app.b2971c25f2dde438c03d.hot-update.js",
    "/js/app.e50da38143ed90634578.hot-update.js": "/js/app.e50da38143ed90634578.hot-update.js",
    "/js/app.6f4e2f3de9e0c00b1db7.hot-update.js": "/js/app.6f4e2f3de9e0c00b1db7.hot-update.js"
}
